sync_clip/__init__.py
sync_clip/cli.py
sync_clip/monitor.py
sync_clip/remote/__init__.py
sync_clip/remote/client.py
sync_clip/remote/server.py
sync_clip/stuff/__init__.py
sync_clip/stuff/clipboards.py
sync_clip/stuff/sync_signal.py
sync_clip/utils/__init__.py
sync_clip/utils/utiil_image.py
sync_clip/utils/util_hash.py
sync_clip/utils/util_log.py
sync_clip/utils/util_path.py
sync_clip/utils/util_thread.py
sync_clip-0.2.0.data/data/requirements/requirements.txt
sync_clip-0.2.0.dist-info/LICENSE
sync_clip-0.2.0.dist-info/METADATA
sync_clip-0.2.0.dist-info/WHEEL
sync_clip-0.2.0.dist-info/entry_points.txt
sync_clip-0.2.0.dist-info/top_level.txt
sync_clip-0.2.0.dist-info/RECORD
