Metadata-Version: 2.2
Name: sync-clip
Version: 0.2.0
Summary: A cross platform clipboard synchronous tool, supports synchronized `text`and screenshots (PNG), support os system: Windows, Linux
Home-page: https://github.com/yujun2647/sync-clip
Download-URL: 
Author: walkerjun
Author-email: yujun2647@163.com
License: Apache-2.0
Requires-Python: >=3.6
License-File: LICENSE
Requires-Dist: pillow
Requires-Dist: pywin32; platform_system == "Windows"
Dynamic: author
Dynamic: author-email
Dynamic: description
Dynamic: description-content-type
Dynamic: home-page
Dynamic: license
Dynamic: requires-dist
Dynamic: requires-python
Dynamic: summary
